{
  "Druid1": "Оракул",
  "Druid2": "Шаман",
  "Huntress1": "Амазонка",
  "Huntress2": "Ходящая среди духов",
  "Huntress3": "Ритуалист",
  "Mercenary1": "Тактик",
  "Mercenary2": "Охотник на ведьм",
  "Mercenary3": "Легионер каменитов",
  "Monk1": "Мастер боевых искусств",
  "Monk2": "Заклинатель стихий",
  "Monk3": "Служитель Чаюлы",
  "Ranger1": "Снайпер",
  "Ranger3": "Следопыт",
  "Sorceress1": "Ткач бурь",
  "Sorceress2": "Хрономант",
  "Sorceress3": "Ученица Варашты",
  "Warrior1": "Титан",
  "Warrior2": "Вестник войны",
  "Warrior3": "Кузнец Китавы",
  "Witch1": "Инферналист",
  "Witch2": "Маг крови",
  "Witch3": "Лич",
  "Witch3b": "Лич Бездны"
}
