{
  "attack_cast_movement_speed_+%[0]": "Nearby Allies have #% increased Attack, Cast and Movement Speed",
  "attack_cast_movement_speed_+%[1]": "Nearby Allies have #% reduced Attack, Cast and Movement Speed",
  "base_chaos_damage_resistance_%[0]": "Nearby Enemies have #% to Chaos Resistance",
  "base_cold_damage_resistance_%[0]": "Nearby Enemies have #% to Cold Resistance",
  "base_cooldown_speed_+%[0]": "Nearby Enemies have #% increased Cooldown Recovery Rate",
  "base_cooldown_speed_+%[1]": "Nearby Enemies have #% reduced Cooldown Recovery Rate",
  "base_critical_strike_multiplier_+[0]": "Nearby Enemies have #% increased Critical Damage Bonus",
  "base_critical_strike_multiplier_+[1]": "Nearby Enemies have #% reduced Critical Damage Bonus",
  "base_movement_velocity_+%[0]": "You and nearby Allies have #% increased Movement Speed",
  "base_movement_velocity_+%[1]": "You and nearby Allies have #% reduced Movement Speed",
  "base_skill_area_of_effect_+%[0]": "Nearby Allies have #% increased Area of Effect",
  "base_skill_area_of_effect_+%[1]": "Nearby Allies have #% reduced Area of Effect",
  "blinded[0]": "Nearby Enemies are Blinded",
  "chance_to_be_frozen_%[0]": "Nearby Enemies have #% chance to be Frozen when Hit",
  "chance_to_be_ignited_%[0]": "Nearby Enemies have #% chance to be Ignited when Hit",
  "chance_to_be_shocked_%[0]": "Nearby Enemies have #% chance to be Shocked when Hit",
  "chance_to_intimidate_on_hit_%[0]": "Nearby Allies have #% chance to Intimidate Enemies for 4 seconds on Hit",
  "chance_to_intimidate_on_hit_%[1]": "Nearby Allies Intimidate Enemies for 4 seconds on Hit",
  "chance_to_unnerve_on_hit_%[0]": "Nearby Allies have #% chance to Unnerve Enemies for 4 seconds on Hit",
  "chance_to_unnerve_on_hit_%[1]": "Nearby Allies Unnerve Enemies for 4 seconds on Hit",
  "damage_+%[0]": "Nearby Allies deal #% increased Damage",
  "damage_+%[1]": "Nearby Enemies deal #% reduced Damage",
  "damage_over_time_+%_while_hindered[0]": "Nearby Hindered Enemies deal #% increased Damage over Time",
  "damage_over_time_+%_while_hindered[1]": "Nearby Hindered Enemies deal #% reduced Damage over Time",
  "elemental_damage_taken_+%[0]": "Nearby Enemies take #% increased Elemental Damage",
  "elemental_damage_taken_+%[1]": "Nearby Enemies take #% reduced Elemental Damage",
  "global_cannot_crit[0]": "Nearby Enemies cannot deal Critical Hits",
  "has_tailwind[0]": "You and nearby Allies have Tailwind",
  "hit_damage_+%_while_chilled[0]": "Nearby Chilled Enemies deal #% increased Damage with Hits",
  "hit_damage_+%_while_chilled[1]": "Nearby Chilled Enemies deal #% reduced Damage with Hits",
  "inquisitor_aura_elemental_damage_+%_final[0]": "Nearby Enemies deal #% more Elemental Damage",
  "inquisitor_aura_elemental_damage_+%_final[1]": "Nearby Enemies deal #% less Elemental Damage",
  "life_regeneration_rate_+%[0]": "Nearby Enemies have #% increased Life Regeneration rate",
  "life_regeneration_rate_+%[1]": "Nearby Enemies have #% reduced Life Regeneration rate",
  "life_regeneration_rate_per_minute_%[0]": "You and nearby Allies Regenerate #% of maximum Life per second",
  "minimum_added_physical_damage_per_impaled_on_enemy maximum_added_physical_damage_per_impaled_on_enemy[0]": "You and nearby Allies deal # to # added Physical Damage for\neach Impale on Enemy"
}
