{
  "accuracy_rating_+%[0]": "Banner grants #% increased Accuracy Rating to You and Allies",
  "accuracy_rating_+%[1]": "Banner grants #% reduced Accuracy Rating to You and Allies",
  "additional_block_%[0]": "Banner grants #% Chance to Block Attack Damage to You and Allies",
  "armour_evasion_banner_critical_strike_chance_+%[0]": "Banner applies #% increased Critical Strike Chance to Enemies",
  "armour_evasion_banner_critical_strike_chance_+%[1]": "Banner applies #% reduced Critical Strike Chance to Enemies",
  "banner_area_of_effect_+%_final_per_resource[0]": "#% more Area of Effect per Valour consumed",
  "banner_area_of_effect_+%_final_per_resource[1]": "#% less Area of Effect per Valour consumed",
  "banner_buff_effect_+%_final_per_resource[0]": "#% more Aura effect per Valour consumed",
  "banner_buff_effect_+%_final_per_resource[1]": "#% less Aura effect per Valour consumed",
  "base_can_gain_banner_resource can_gain_banner_resource_while_banner_is_placed[0]": "While you have no placed Banner, you can gain Valour",
  "base_can_gain_banner_resource can_gain_banner_resource_while_banner_is_placed[1]": "You can gain Valour",
  "base_movement_velocity_+%[0]": "Banner grants #% increased Movement Speed to You and Allies",
  "base_movement_velocity_+%[1]": "Banner grants #% reduced Movement Speed to You and Allies",
  "base_spell_suppression_chance_%[0]": "Banner grants #% chance to Suppress Spell Damage to You and Allies",
  "bleeding_dot_multiplier_+[0]": "Banner grants #% to Damage over Time Multiplier for Bleeding to You and Allies",
  "buff_effect_duration[0]": "Banner lasts # seconds",
  "damage_taken_+_from_suppressed_hits[0]": "Banner grants # Damage taken of each Damage Type from Suppressed Hits to You and Allies",
  "evasion_and_physical_damage_reduction_rating_+%[0]": "Banner grants #% increased Armour and Evasion Rating to You and Allies",
  "evasion_and_physical_damage_reduction_rating_+%[1]": "Banner grants #% reduced Armour and Evasion Rating to You and Allies",
  "impale_debuff_effect_+%[0]": "Banner grants #% increased Impale Effect to You and Allies",
  "impale_debuff_effect_+%[1]": "Banner grants #% reduced Impale Effect to You and Allies",
  "puresteel_banner_accuracy_rating_+%_final[0]": "Banner applies #% more Accuracy Rating to Enemies",
  "puresteel_banner_accuracy_rating_+%_final[1]": "Banner applies #% less Accuracy Rating to Enemies",
  "puresteel_banner_damage_+%_final[0]": "Banner applies #% more Damage to Enemies",
  "puresteel_banner_damage_+%_final[1]": "Banner applies #% less Damage to Enemies",
  "recover_X_life_on_block[0]": "Banner causes you and Allies to Recover # Life when Blocking",
  "war_banner_physical_damage_+%_final_with_melee_skills[0]": "Banner grants #% more Physical Damage with Melee Skills to You and Allies",
  "war_banner_physical_damage_+%_final_with_melee_skills[1]": "Banner grants #% less Physical Damage with Melee Skills to You and Allies"
}
