{
  "Abyss_Boss1": "무광의 공허",
  "Abyss_Boss2": "어둠의 영토",
  "Abyss_Depths1": "심연 지하",
  "Abyss_Depths2": "심연 지하",
  "Abyss_Depths3": "심연 지하",
  "Abyss_Hub": "영혼의 우물",
  "Abyss_Intro": "무광의 통로",
  "Abyss_Pinnacle": "영혼의 우물",
  "BlackTest": "All Black",
  "BossRush_Area1": "보스 러시 지역 1",
  "BossRush_Area2": "보스 러시 지역 2",
  "BossRush_Area3": "보스 러시 지역 3",
  "BreachDomain_01": "뒤틀린 영역",
  "CharacterSelect": "캐릭터 선택",
  "ChayulaLeague": "수호자들의 수도원",
  "ChayulaLeague_Tower": "벌레집 요새",
  "ChayulaLeague_TowerBoss": "벌레집 군락지",
  "CurrentTown": "현재 마을",
  "Delirium_Act1Town": "망상의 복제된 영토",
  "Delirium_Act1Town_Quest": "망상의 복제된 영토",
  "Delirium_Act2Reveal": "가루칸의 무덤",
  "Delirium_Act3Town": "가라앉은 피라미드",
  "Delirium_HungerBoss": "혐오스러운 진창",
  "Design": "Gone Fishing",
  "Design_Lite": "디자인 (라이트)",
  "DruidTrailer": "드루이드 트레일러",
  "EndgameDoodad_BeastGroundZero": "사슬에 매인 짐승",
  "EndgameDoodad_MeteorCrater": "별똥별",
  "ExpeditionLeagueBoss": "칼구르 무덤",
  "ExpeditionLogBook_Atoll": "불모의 산호섬",
  "ExpeditionLogBook_Basin": "고인 분지",
  "ExpeditionLogBook_Digsite": "파헤쳐진 폐허",
  "ExpeditionLogBook_Gully": "진창이 된 고랑",
  "ExpeditionLogBook_Heath": "무너진 하늘의 황야",
  "ExpeditionLogBook_Peninsula": "바위투성이 반도",
  "ExpeditionLogBook_Prairie": "풀이 뜯긴 프레리",
  "ExpeditionLogBook_Reef": "표백된 모래톱",
  "ExpeditionLogBook_Tropical": "우거진 섬",
  "ExpeditionLogBook_Tundra": "차디찬 절벽",
  "ExpeditionLogBook_Wastes": "그을린 암초",
  "ExpeditionSubArea_BlackKnightBoss": "몰락 기사의 무덤",
  "ExpeditionSubArea_Catacomb": "방치된 지하 묘지",
  "ExpeditionSubArea_Cavern": "밀수범 소굴",
  "ExpeditionSubArea_Fissure": "퀴퀴한 틈새",
  "ExpeditionSubArea_Kalguur": "룬 지하 묘지",
  "ExpeditionSubArea_Kalguur_Act1": "사라진 지하 묘지",
  "ExpeditionSubArea_Kalguur_Act2": "거신의 두개골",
  "ExpeditionSubArea_Kalguur_Act3": "신비한 피난처",
  "ExpeditionSubArea_Kalguur_Act4": "버려진 초소",
  "ExpeditionSubArea_Laboratory": "쇠퇴한 실험실",
  "ExpeditionSubArea_Lair": "악취 나는 둥지",
  "ExpeditionSubArea_MedvedBoss": "뻗어 가는 밀림",
  "ExpeditionSubArea_OlrothBoss": "후미진 섬",
  "ExpeditionSubArea_Pond": "유명한 연못",
  "ExpeditionSubArea_Precursor": "고대의 은닉함",
  "ExpeditionSubArea_Sanctuary": "고요한 방",
  "ExpeditionSubArea_Siren": "숨겨진 대수층",
  "ExpeditionSubArea_UhtredBoss": "외딴 사원",
  "ExpeditionSubArea_Vein": "도금된 광맥",
  "ExpeditionSubArea_Volcano": "유황 광산",
  "ExpeditionSubArea_VoranaBoss": "음울한 낭떠러지",
  "G1_1": "강둑",
  "G1_10": "뿌리 동혈",
  "G1_11": "사냥터",
  "G1_12": "프레이쏜",
  "G1_13_1": "오검 농지",
  "G1_13_2": "오검 마을",
  "G1_14": "저택 성벽",
  "G1_15": "오검 저택",
  "G1_2": "클리어펠",
  "G1_3": "진흙 토굴",
  "G1_4": "그렐우드",
  "G1_5": "붉은 계곡",
  "G1_6": "으스스한 덩굴",
  "G1_7": "영원한 자의 공동묘지",
  "G1_8": "집정관의 능묘",
  "G1_9": "배우자의 무덤",
  "G1_WorldMap": "1장",
  "G1_town": "클리어펠 야영지",
  "G2_1": "바스티리 외곽",
  "G2_10_1": "모둔 채석장",
  "G2_10_2": "모둔 광산",
  "G2_11": "드레드노트의 바퀴 자국",
  "G2_12": "드레드노트",
  "G2_13": "세케마의 시련",
  "G2_2": "배반자의 통로",
  "G2_3": "할라니 관문",
  "G2_3a": "할라니 관문",
  "G2_3s": "할라니 관문",
  "G2_4_1": "케스",
  "G2_4_2": "잃어버린 도시",
  "G2_4_3": "묻힌 성소",
  "G2_5_1": "마스토돈 불모지",
  "G2_5_2": "뼈 구덩이",
  "G2_6": "거신의 계곡",
  "G2_7": "거신 석굴",
  "G2_8": "데샤르",
  "G2_8a": "데샤르",
  "G2_9_1": "통곡의 길",
  "G2_9_2": "데샤르의 첨탑",
  "G2_WorldMap": "2장",
  "G2_town": "아르듀라 카라반",
  "G3_1": "모래에 휩쓸린 습지",
  "G3_10": "혼돈의 시련",
  "G3_10_Airlock": "혼돈의 사원",
  "G3_11": "오물의 정점",
  "G3_12": "코펙의 사원",
  "G3_14": "웃자알",
  "G3_15": "카마사의 도서관",
  "G3_16": "아고라트",
  "G3_17": "검은 내실",
  "G3_2_1": "들끓는 불모지",
  "G3_2_2": "마틀란 수로",
  "G3_3": "밀림 유적",
  "G3_4": "독액 지하실",
  "G3_5": "키메랄 습지대",
  "G3_6_1": "지콰니의 기계실",
  "G3_6_2": "지콰니의 지성소",
  "G3_7": "아자크 습지대",
  "G3_8": "물에 잠긴 도시",
  "G3_9": "녹아내린 금고",
  "G3_WorldMap": "3장",
  "G3_town": "지구라트 야영지",
  "G4_10": "발굴터",
  "G4_11_1a": "응가카누",
  "G4_11_1b": "응가카누",
  "G4_11_2": "부족의 심장부",
  "G4_13": "약탈의 거점",
  "G4_14": "부패한 염수단 만",
  "G4_1_1": "혈족의 섬",
  "G4_1_2": "화산 땅굴",
  "G4_2_1": "닻의 만",
  "G4_2_2": "여정의 끝",
  "G4_3_1": "와카파누 섬",
  "G4_3_2": "노래하는 암굴",
  "G4_4_1": "히네코라의 눈",
  "G4_4_2": "죽음의 전당",
  "G4_4_3": "선조들의 심판",
  "G4_5_1": "버려진 감옥",
  "G4_5_2": "독방 감금실",
  "G4_7": "때까치 섬",
  "G4_8a": "아라스타스",
  "G4_8b": "아라스타스",
  "G4_9_": "부패의 섬",
  "G4_WorldMap": "4장",
  "G4_town": "킹스마치",
  "G6_WorldMap": "6장",
  "G_Endgame_Town": "지구라트 피난처",
  "G_login": "로그인 장면",
  "GuildHideout__": "내 길드 은신처",
  "HideoutArcaneIsle": "비전의 섬 은신처",
  "HideoutArenaBlackStar_": "극성의 은신처",
  "HideoutArenaEaterOfWorlds": "얽힌 은신처",
  "HideoutArenaElder": "공허 은신처",
  "HideoutArenaGraveyardTrio": "매장된 은신처",
  "HideoutArenaIncursion": "붉은 여왕의 방 은신처",
  "HideoutArenaInfiniteHunger": "끓어오르는 은신처",
  "HideoutArenaKulemak": "검은 대성당 은신처",
  "HideoutArenaMaven": "혹독한 시련의 은신처",
  "HideoutArenaSearingExarch": "이글거리는 은신처",
  "HideoutAtziriArena": "타락한 은신처",
  "HideoutAzuriteCave": "남동석 암굴 은신처",
  "HideoutBeaconOfSalvation": "구원의 등대 은신처",
  "HideoutBlankAbyss": "무한한 심연 은신처",
  "HideoutBlankBlack": "검은 공허 은신처",
  "HideoutBlankCity": "확산된 도심 은신처",
  "HideoutBlankClouds": "광대한 창공 은신처",
  "HideoutBlankCrypt": "능묘 은신처",
  "HideoutBlankDesert": "끝없는 사막 은신처",
  "HideoutBlankDesert2": "바스티리 평야 은신처",
  "HideoutBlankDirt": "영원의 황무지 은신처",
  "HideoutBlankGrass": "광활한 초원 은신처",
  "HideoutBlankJungle": "밀림 빈터 은신처",
  "HideoutBlankMountain": "높은 산의 고원 은신처",
  "HideoutBlankSea": "아득한 바다 은신처",
  "HideoutBlankSnow": "드넓은 빙하 은신처",
  "HideoutBlankUrban": "시민 광장 은신처",
  "HideoutBlankVolcanicCave": "화산 동굴 은신처",
  "HideoutCanal": "운하 은신처",
  "HideoutCanopy": "우듬지 은신처",
  "HideoutCave": "물에 잠긴 은신처",
  "HideoutChaos": "혼돈 은신처",
  "HideoutChiyouSpring": "치우 은신처",
  "HideoutColossalTitan": "거신의 정점 은신처",
  "HideoutCosmicAtlas": "아틀라스 은신처",
  "HideoutDaressoArena": "용사의 은신처",
  "HideoutDark": "유령이 밝힌 묘지 은신처",
  "HideoutDarkwood": "흑단목 은신처",
  "HideoutDominusArena": "불굴의 은신처",
  "HideoutDoomguard": "파멸수호병 은신처",
  "HideoutDreadnought": "드레드노트 은신처",
  "HideoutFarmlands": "농지 은신처",
  "HideoutFelled": "벌채된 은신처",
  "HideoutGrinding": "연마하는 은신처",
  "HideoutHasina": "선술집 은신처",
  "HideoutHourglass": "모래시계 은신처",
  "HideoutHumanoidPet": "인간형 애완동물 은신처",
  "HideoutInnocenceArena": "순수한 은신처",
  "HideoutKaomArena": "분개한 은신처",
  "HideoutKitavaArenaAct10": "굶주린 은신처",
  "HideoutLight": "시간 기록자의 은신처",
  "HideoutLimestone": "석회암 은신처",
  "HideoutLunarisSolarisArena": "그늘진 은신처",
  "HideoutMonolith": "거석 은신처",
  "HideoutOlrothArena": "선대의 은신처",
  "HideoutPietyArena": "소름 끼치는 은신처",
  "HideoutPillarsOfArun": "높이 솟은 은신처",
  "HideoutPrison": "감옥 은신처",
  "HideoutRacetrack": "바스티리 경주장 은신처",
  "HideoutRitualLeague": "의식술사의 은신처",
  "HideoutSacrifice": "희생의 정점 은신처",
  "HideoutShaperArena": "형성된 은신처",
  "HideoutShipgraveyard": "난파선 은신처",
  "HideoutShipwreck": "크라켄의 만 은신처",
  "HideoutShoreline": "해안선 은신처",
  "HideoutShrine": "성소 은신처",
  "HideoutSpace": "천공의 성운 은신처",
  "HideoutSummit": "신들의 고원 은신처",
  "HideoutSunkenPalace": "가라앉은 궁전 은신처",
  "HideoutSunspire": "태양첨탑 은신처",
  "HideoutSynthesisHub": "결합 은신처",
  "HideoutTencentApocalypse": "대재앙 은신처",
  "HideoutThaumaturgy": "마석학 은신처",
  "HideoutTranscendent": "초월한 은신처",
  "HideoutTwisted": "뒤틀린 은신처",
  "HideoutVampireManor": "피 강탈자 저택 은신처",
  "HideoutVerdant": "무성한 정점 은신처",
  "HideoutVeritaniaArena": "대속자의 은신처",
  "HideoutYaochi": "요지 은신처",
  "IncursionHub": "바알 유적",
  "IncursionHubEndgame": "바알 유적",
  "IncursionTemple": "앗지리의 사원",
  "IncursionTemplePresent": "사라진 사원",
  "KaruiBossShowcase": "카루이 보스 소개",
  "KaruiShowcase": "부족의 심장부",
  "MapAlpineRidge": "고산지대 산등성이",
  "MapAridPlains": "메마른 평야",
  "MapArroyo": "마른 하천",
  "MapAugury": "점술",
  "MapAzmerianRanges": "아즈메리 산맥",
  "MapBackwash": "역류",
  "MapBastille": "방어탑",
  "MapBazaar": "장터",
  "MapBloodwood": "피숲",
  "MapBloomingField": "꽃피는 들판",
  "MapBluff": "절벽",
  "MapBurialBog": "매장용 습지대",
  "MapCaldera": "칼데라",
  "MapCanyon": "협곡",
  "MapCavernCity": "성스러운 저수지",
  "MapCenotes": "세노테",
  "MapChannel": "물길",
  "MapChasm": "절벽길",
  "MapCliffside": "낭떠러지",
  "MapCreek": "개울",
  "MapCrimsonShores": "붉은 물가",
  "MapCrypt": "묘실",
  "MapDecay": "부패",
  "MapDeforestation": "벌채지",
  "MapDerelictMansion": "방치된 저택",
  "MapDeserted": "인적 없는",
  "MapEpitaph": "비문",
  "MapExcavation": "발굴 현장",
  "MapFlotsam": "표류물",
  "MapForge": "대장간",
  "MapFortress": "요새",
  "MapFrozenFalls": "얼어붙은 폭포",
  "MapGeode": "정동석",
  "MapGreenhouse": "온실",
  "MapGrimhaven": "그림헤이븐",
  "MapHeadland": "갑",
  "MapHiddenGrotto": "숨겨진 석굴",
  "MapHideoutCanal_Claimable": "운하 은신처",
  "MapHideoutFarmlands_Claimable": "농지 은신처",
  "MapHideoutFelled_Claimable": "벌채된 은신처",
  "MapHideoutLimestone_Claimable": "석회암 은신처",
  "MapHideoutPrison_Claimable": "감옥 은신처",
  "MapHideoutShoreline_Claimable": "해안선 은신처",
  "MapHideoutShrine_Claimable": "성소 은신처",
  "MapHive": "벌레집",
  "MapIceCave": "얼음 동굴",
  "MapInferno": "지옥불",
  "MapKarst": "카르스트",
  "MapLeaguePortal": "세계관문",
  "MapLoftySummit": "높은 정상",
  "MapLostTowers": "잃어버린 탑",
  "MapMarrow": "골수",
  "MapMesa": "메사",
  "MapMezzanine": "중층",
  "MapMineshaft": "갱도",
  "MapMire": "진창",
  "MapMonument": "기념물",
  "MapMortuary": "시체 안치소",
  "MapMothersoul_Female": "가모장의 전당",
  "MapMothersoul_Female_Quest": "가모장의 전당",
  "MapMothersoul_Male": "가부장의 전당",
  "MapMothersoul_Male_Quest": "가부장의 전당",
  "MapNecropolis": "매장지",
  "MapOasis": "오아시스",
  "MapOrbalasCrossing": "오발라의 교차로",
  "MapOrnateChambers": "화려한 석실",
  "MapOutlands": "외곽 지역",
  "MapOvergrown": "무성한 땅",
  "MapPenitentiary": "교도소",
  "MapPit": "구덩이",
  "MapPlantation": "플랜테이션",
  "MapPort": "항만",
  "MapPrecipice": "벼랑",
  "MapPrecursorTower": "선도자 탑",
  "MapPrecursorTowerDesert": "선도자 탑",
  "MapPrecursorTowerForest": "선도자 탑",
  "MapPrecursorTowerGrass": "선도자 탑",
  "MapPrecursorTowerMountain": "선도자 탑",
  "MapPrecursorTowerSwamp": "선도자 탑",
  "MapRavine": "심곡",
  "MapRazedFields": "초토화된 들판",
  "MapReservoir": "저수지",
  "MapRiverhold": "강요새",
  "MapRiverside": "강변",
  "MapRockpools": "바위틈 웅덩이",
  "MapRugosa": "루고사",
  "MapRupture": "파열",
  "MapRustbowl": "녹그릇",
  "MapSanctuary": "성역",
  "MapSandspit": "모래 구덩이",
  "MapSavanna": "사바나",
  "MapSeepage": "누수",
  "MapSevenWaters": "합류지",
  "MapSinkhole": "낙수혈",
  "MapSinterRift": "유황화 균열",
  "MapSlash": "절창",
  "MapSlick": "미끌",
  "MapSnowfall": "강설",
  "MapSpiderWoods": "거미 숲",
  "MapSpring_": "샘",
  "MapSteamingSprings": "증기 뿜는 샘",
  "MapSteppe": "아열대 초원",
  "MapStronghold": "요새",
  "MapSulphuricCaverns": "유황 동굴",
  "MapSump": "웅덩이",
  "MapSunTemple": "태양의 사원",
  "MapSwampTower": "가라앉는 첨탑",
  "MapSwarm": "무리",
  "MapTerrace": "테라스",
  "MapTrenches": "참호",
  "MapUberBoss_CopperCitadel": "구리의 성채",
  "MapUberBoss_CopperCitadel_Quest": "구리의 성채",
  "MapUberBoss_Delirium": "시든 버드나무",
  "MapUberBoss_Divinity": "기원의 탑",
  "MapUberBoss_FallenStar": "킹스마치의 폐허",
  "MapUberBoss_IronCitadel": "철의 성채",
  "MapUberBoss_IronCitadel_Quest": "서쪽 수수께끼 석실",
  "MapUberBoss_JadeCitadel": "비취 군도",
  "MapUberBoss_Monolith": "불타는 거석",
  "MapUberBoss_Ritual": "캐어 타르스",
  "MapUberBoss_StoneCitadel": "돌의 성채",
  "MapUberBoss_StoneCitadel_Quest": "동쪽 수수께끼 석실",
  "MapUniqueCastaway": "조난자",
  "MapUniqueFreight_": "화물",
  "MapUniqueInitialTower": "선도자 탑",
  "MapUniqueLake": "분열된 호수",
  "MapUniqueMegalith": "에조미어 거석",
  "MapUniqueMerchant01_Chimeral": "상인의 야영지",
  "MapUniqueMerchant01_Oasis": "자도의 야영지",
  "MapUniqueMerchant01_Sandswept": "상인의 야영지",
  "MapUniqueMerchant02_Crimson": "상인의 야영지",
  "MapUniqueMerchant02_Farmland": "상인의 야영지",
  "MapUniqueMerchant03_Beach": "한 순간의 선",
  "MapUniqueMerchant03_Raft": "한 순간의 선",
  "MapUniqueMerchant03_Tropical": "한 순간의 선",
  "MapUniqueMerchant04_PirateShip": "항해",
  "MapUniqueReactor_01": "서쪽 관문",
  "MapUniqueReactor_02": "고대 관문",
  "MapUniqueReactor_03": "동쪽 관문",
  "MapUniqueReactor_04": "선택받은 자의 장소",
  "MapUniqueSelenite": "고요한 동굴",
  "MapUniqueUntaintedParadise": "때묻지 않은 낙원",
  "MapUniqueVault": "카마사의 금고",
  "MapUniqueWildwood": "취록의 야생림",
  "MapVaalCity": "바알 도시",
  "MapVaalFactory": "조립 시설",
  "MapVaalFoundry": "녹아내린 금고실",
  "MapVaalVault": "봉인된 금고실",
  "MapVaalVillage": "바알 마을",
  "MapVoidReliquary": "성유물 보관실 금고",
  "MapWaywardIsle": "다스리기 힘든 섬",
  "MapWetlands": "습지대",
  "MapWillow": "버드나무",
  "MapWoodland": "밀림",
  "Map_HildaCampsite": "힐다의 야영지",
  "NULL": "NULL",
  "P1_1": "그을린 농지",
  "P1_2": "세를의 두름돌",
  "P1_3": "검은 숲",
  "P1_4": "홀튼",
  "P1_5": "울븐홀드",
  "P1_6": "홀튼 영지",
  "P1_Town": "피난처",
  "P2_1": "카리 교차로",
  "P2_2": "카탈의 웅덩이",
  "P2_3": "셀 카리 성역",
  "P2_5": "갈라이 문",
  "P2_6": "키마",
  "P2_7": "키마 저수지",
  "P2_Town": "카리 장터",
  "P3_1": "잿빛 수림",
  "P3_2": "크리아 마을",
  "P3_3": "빙하 호수",
  "P3_4": "울부짖는 동굴",
  "P3_5": "크리아 봉우리",
  "P3_6": "아로새겨진 심곡",
  "P3_7": "쿠아식 금고실",
  "P3_Town": "풀숲",
  "PersonalHideout": "은신처",
  "PrecursorVault": "선도자 금고실",
  "Programming": "프로그래밍 월드",
  "Programming_Lite": "프로그래밍 월드",
  "RitualLeagueBoss": "허무의 핵심",
  "Sanctum_1": "세케마의 시련",
  "Sanctum_1_Foyer_1": "세케마의 시련",
  "Sanctum_1_Foyer_2": "세케마의 시련",
  "Sanctum_1_Foyer_3": "세케마의 시련",
  "Sanctum_2": "세케마의 시련",
  "Sanctum_2_Foyer_1": "세케마의 시련",
  "Sanctum_2_Foyer_2": "세케마의 시련",
  "Sanctum_2_Foyer_3": "세케마의 시련",
  "Sanctum_3": "세케마의 시련",
  "Sanctum_3_Foyer_1": "세케마의 시련",
  "Sanctum_3_Foyer_2": "세케마의 시련",
  "Sanctum_3_Foyer_3": "세케마의 시련",
  "Sanctum_4": "세케마의 시련",
  "Sanctum_4_Foyer_1": "세케마의 시련",
  "Sanctum_4_Foyer_2": "세케마의 시련",
  "Sanctum_4_Foyer_3": "세케마의 시련",
  "TN_WorldMap": "아틀라스"
}
